<?xml version="1.0"?>
<engine>
    <paypal>
        <title>Paypal</title>
        <sort_order>1</sort_order>
        <model>aw_sarp2/engine_paypal_engine</model>
        <payment_methods>
            <item>paypal_express</item>
        </payment_methods>
    </paypal>
    <authorizenet>
        <title>Authorize.net</title>
        <sort_order>2</sort_order>
        <model>aw_sarp2/engine_authorizenet_engine</model>
        <payment_methods>
            <item>authorizenet</item>
        </payment_methods>
    </authorizenet>
</engine>